cpap_py/__init__.py
cpap_py/_version.py
cpap_py/datalog_parser.py
cpap_py/edf_parser.py
cpap_py/identification.py
cpap_py/loader.py
cpap_py/settings_parser.py
cpap_py/str_parser.py
cpap_py/utils.py
cpap_py-1.0.0.dist-info/licenses/LICENSE
cpap_py-1.0.0.dist-info/METADATA
cpap_py-1.0.0.dist-info/WHEEL
cpap_py-1.0.0.dist-info/top_level.txt
cpap_py-1.0.0.dist-info/RECORD
