Metadata-Version: 2.4
Name: cpap-py
Version: 1.0.0
Summary: A comprehensive Python library for parsing and analyzing ResMed CPAP machine data
Home-page: https://github.com/dynacylabs/cpap-py
Author: DynacyLabs
License: MIT
Project-URL: Homepage, https://github.com/dynacylabs/cpap-py
Project-URL: Documentation, https://github.com/dynacylabs/cpap-py/blob/main/README.md
Project-URL: Repository, https://github.com/dynacylabs/cpap-py
Project-URL: Issues, https://github.com/dynacylabs/cpap-py/issues
Keywords: cpap,resmed,sleep-apnea,medical-devices,edf
Classifier: Development Status :: 3 - Alpha
Classifier: Intended Audience :: Developers
Classifier: Intended Audience :: Healthcare Industry
Classifier: License :: OSI Approved :: MIT License
Classifier: Programming Language :: Python :: 3
Classifier: Programming Language :: Python :: 3.9
Classifier: Programming Language :: Python :: 3.10
Classifier: Programming Language :: Python :: 3.11
Classifier: Programming Language :: Python :: 3.12
Classifier: Topic :: Scientific/Engineering :: Medical Science Apps.
Requires-Python: >=3.8
License-File: LICENSE
Requires-Dist: pyedflib>=0.1.30
Requires-Dist: numpy>=1.20.0
Requires-Dist: pandas>=1.3.0
Requires-Dist: pydantic>=2.0.0
Requires-Dist: python-dateutil>=2.8.0
Provides-Extra: dev
Requires-Dist: pytest>=7.0.0; extra == "dev"
Requires-Dist: pytest-cov>=4.0.0; extra == "dev"
Requires-Dist: pytest-mock>=3.10.0; extra == "dev"
Requires-Dist: coverage>=7.0.0; extra == "dev"
Requires-Dist: black>=23.0.0; extra == "dev"
Requires-Dist: ruff>=0.1.0; extra == "dev"
Requires-Dist: mypy>=1.0.0; extra == "dev"
Provides-Extra: test
Requires-Dist: pytest>=7.0.0; extra == "test"
Requires-Dist: pytest-cov>=4.0.0; extra == "test"
Requires-Dist: pytest-mock>=3.10.0; extra == "test"
Requires-Dist: coverage>=7.0.0; extra == "test"
Dynamic: home-page
Dynamic: license-file
Dynamic: requires-python
